{
    "Files": {
        "/tmp/bubblewrap.zip4269052694/.editorconfig": {
            "Path": "/tmp/bubblewrap.zip4269052694/.editorconfig",
            "SHA256": "",
            "Size": 0,
            "Skipped": "data file",
            "RiskScore": 0
        },
        "/tmp/bubblewrap.zip4269052694/.github/workflows/check.yml": {
            "Path": "/tmp/bubblewrap.zip4269052694/.github/workflows/check.yml",
            "SHA256": "",
            "Size": 0,
            "Skipped": "data file",
            "RiskScore": 0
        },
        "/tmp/bubblewrap.zip4269052694/CODE-OF-CONDUCT.md": {
            "Path": "/tmp/bubblewrap.zip4269052694/CODE-OF-CONDUCT.md",
            "SHA256": "",
            "Size": 0,
            "Skipped": "data file",
            "RiskScore": 0
        },
        "/tmp/bubblewrap.zip4269052694/COPYING": {
            "Path": "/tmp/bubblewrap.zip4269052694/COPYING",
            "SHA256": "",
            "Size": 0,
            "Skipped": "data file",
            "RiskScore": 0
        },
        "/tmp/bubblewrap.zip4269052694/LICENSE": {
            "Path": "/tmp/bubblewrap.zip4269052694/LICENSE",
            "SHA256": "",
            "Size": 0,
            "Skipped": "data file",
            "RiskScore": 0
        },
        "/tmp/bubblewrap.zip4269052694/README.md": {
            "Path": "/tmp/bubblewrap.zip4269052694/README.md",
            "SHA256": "",
            "Size": 0,
            "Skipped": "data file",
            "RiskScore": 0
        },
        "/tmp/bubblewrap.zip4269052694/SECURITY.md": {
            "Path": "/tmp/bubblewrap.zip4269052694/SECURITY.md",
            "SHA256": "",
            "Size": 0,
            "Skipped": "data file",
            "RiskScore": 0
        },
        "/tmp/bubblewrap.zip4269052694/bind-mount.c": {
            "Path": "/tmp/bubblewrap.zip4269052694/bind-mount.c",
            "SHA256": "",
            "Size": 0,
            "RiskScore": 0
        },
        "/tmp/bubblewrap.zip4269052694/bind-mount.h": {
            "Path": "/tmp/bubblewrap.zip4269052694/bind-mount.h",
            "SHA256": "",
            "Size": 0,
            "RiskScore": 0
        },
        "/tmp/bubblewrap.zip4269052694/bubblewrap.c": {
            "Path": "/tmp/bubblewrap.zip4269052694/bubblewrap.c",
            "SHA256": "",
            "Size": 0,
            "RiskScore": 0
        },
        "/tmp/bubblewrap.zip4269052694/bubblewrap.jpg": {
            "Path": "/tmp/bubblewrap.zip4269052694/bubblewrap.jpg",
            "SHA256": "",
            "Size": 0,
            "Skipped": "data file",
            "RiskScore": 0
        },
        "/tmp/bubblewrap.zip4269052694/bwrap.xml": {
            "Path": "/tmp/bubblewrap.zip4269052694/bwrap.xml",
            "SHA256": "",
            "Size": 0,
            "Skipped": "data file",
            "RiskScore": 0
        },
        "/tmp/bubblewrap.zip4269052694/ci/builddeps.sh": {
            "Path": "/tmp/bubblewrap.zip4269052694/ci/builddeps.sh",
            "SHA256": "",
            "Size": 0,
            "RiskScore": 0
        },
        "/tmp/bubblewrap.zip4269052694/completions/bash/bwrap": {
            "Path": "/tmp/bubblewrap.zip4269052694/completions/bash/bwrap",
            "SHA256": "",
            "Size": 0,
            "Skipped": "data file",
            "RiskScore": 0
        },
        "/tmp/bubblewrap.zip4269052694/completions/bash/meson.build": {
            "Path": "/tmp/bubblewrap.zip4269052694/completions/bash/meson.build",
            "SHA256": "",
            "Size": 0,
            "Skipped": "data file",
            "RiskScore": 0
        },
        "/tmp/bubblewrap.zip4269052694/completions/meson.build": {
            "Path": "/tmp/bubblewrap.zip4269052694/completions/meson.build",
            "SHA256": "",
            "Size": 0,
            "Skipped": "data file",
            "RiskScore": 0
        },
        "/tmp/bubblewrap.zip4269052694/completions/zsh/_bwrap": {
            "Path": "/tmp/bubblewrap.zip4269052694/completions/zsh/_bwrap",
            "SHA256": "",
            "Size": 0,
            "Skipped": "data file",
            "RiskScore": 0
        },
        "/tmp/bubblewrap.zip4269052694/completions/zsh/meson.build": {
            "Path": "/tmp/bubblewrap.zip4269052694/completions/zsh/meson.build",
            "SHA256": "",
            "Size": 0,
            "Skipped": "data file",
            "RiskScore": 0
        },
        "/tmp/bubblewrap.zip4269052694/demos/bubblewrap-shell.sh": {
            "Path": "/tmp/bubblewrap.zip4269052694/demos/bubblewrap-shell.sh",
            "SHA256": "",
            "Size": 0,
            "RiskScore": 0
        },
        "/tmp/bubblewrap.zip4269052694/demos/flatpak-run.sh": {
            "Path": "/home/lyvd/panic-at-the-distro-malicious-apks/datasets/upstream_repos/bubblewrap.zip ∴ /demos/flatpak-run.sh",
            "SHA256": "571dbc8beb5a43236dd4142345ad74c6a536027820747ac9f6eea86925c23610",
            "Size": 2642,
            "Behaviors": [
                {
                    "Description": "high-risk fetch command",
                    "MatchStrings": [
                        "curl -O http://sdk.gnome.org/nightly/keys/nightly.gpg"
                    ],
                    "RiskScore": 3,
                    "RiskLevel": "HIGH",
                    "RuleURL": "https://github.com/chainguard-dev/malcontent/blob/main/rules/net/fetch-suspicious.yara#high_fetch_command_val",
                    "ID": "net/fetch/suspicious",
                    "RuleName": "high_fetch_command_val"
                },
                {
                    "Description": "hidden path in a system directory",
                    "MatchStrings": [
                        "/tmp/.X11"
                    ],
                    "RiskScore": 3,
                    "RiskLevel": "HIGH",
                    "RuleURL": "https://github.com/chainguard-dev/malcontent/blob/main/rules/ref/path/hidden.yara#hidden_short_path",
                    "ID": "ref/path/hidden",
                    "RuleName": "hidden_short_path"
                }
            ],
            "RiskScore": 3,
            "RiskLevel": "HIGH"
        },
        "/tmp/bubblewrap.zip4269052694/demos/flatpak.bpf": {
            "Path": "/tmp/bubblewrap.zip4269052694/demos/flatpak.bpf",
            "SHA256": "",
            "Size": 0,
            "Skipped": "data file",
            "RiskScore": 0
        },
        "/tmp/bubblewrap.zip4269052694/demos/userns-block-fd.py": {
            "Path": "/tmp/bubblewrap.zip4269052694/demos/userns-block-fd.py",
            "SHA256": "",
            "Size": 0,
            "RiskScore": 0
        },
        "/tmp/bubblewrap.zip4269052694/meson.build": {
            "Path": "/tmp/bubblewrap.zip4269052694/meson.build",
            "SHA256": "",
            "Size": 0,
            "Skipped": "data file",
            "RiskScore": 0
        },
        "/tmp/bubblewrap.zip4269052694/meson_options.txt": {
            "Path": "/tmp/bubblewrap.zip4269052694/meson_options.txt",
            "SHA256": "",
            "Size": 0,
            "Skipped": "data file",
            "RiskScore": 0
        },
        "/tmp/bubblewrap.zip4269052694/network.c": {
            "Path": "/tmp/bubblewrap.zip4269052694/network.c",
            "SHA256": "",
            "Size": 0,
            "RiskScore": 0
        },
        "/tmp/bubblewrap.zip4269052694/network.h": {
            "Path": "/tmp/bubblewrap.zip4269052694/network.h",
            "SHA256": "",
            "Size": 0,
            "RiskScore": 0
        },
        "/tmp/bubblewrap.zip4269052694/packaging/bubblewrap.spec": {
            "Path": "/tmp/bubblewrap.zip4269052694/packaging/bubblewrap.spec",
            "SHA256": "",
            "Size": 0,
            "Skipped": "data file",
            "RiskScore": 0
        },
        "/tmp/bubblewrap.zip4269052694/release-checklist.md": {
            "Path": "/tmp/bubblewrap.zip4269052694/release-checklist.md",
            "SHA256": "",
            "Size": 0,
            "Skipped": "data file",
            "RiskScore": 0
        },
        "/tmp/bubblewrap.zip4269052694/tests/libtest-core.sh": {
            "Path": "/tmp/bubblewrap.zip4269052694/tests/libtest-core.sh",
            "SHA256": "",
            "Size": 0,
            "RiskScore": 0
        },
        "/tmp/bubblewrap.zip4269052694/tests/libtest.sh": {
            "Path": "/tmp/bubblewrap.zip4269052694/tests/libtest.sh",
            "SHA256": "",
            "Size": 0,
            "RiskScore": 0
        },
        "/tmp/bubblewrap.zip4269052694/tests/meson.build": {
            "Path": "/tmp/bubblewrap.zip4269052694/tests/meson.build",
            "SHA256": "",
            "Size": 0,
            "Skipped": "data file",
            "RiskScore": 0
        },
        "/tmp/bubblewrap.zip4269052694/tests/test-run.sh": {
            "Path": "/home/lyvd/panic-at-the-distro-malicious-apks/datasets/upstream_repos/bubblewrap.zip ∴ /tests/test-run.sh",
            "SHA256": "17c33a1682ebb79d0e29690b93baa9753adde6a809091de09a02fa9cf36337b1",
            "Size": 22791,
            "Behaviors": [
                {
                    "Description": "unusual one-liners involving /tmp",
                    "MatchStrings": [
                        "--bind /etc/shadow /tmp/foo cat /tmp/foo;",
                        "UNREADABLE /tmp/foo cat /tmp/foo;"
                    ],
                    "RiskScore": 3,
                    "RiskLevel": "HIGH",
                    "RuleURL": "https://github.com/chainguard-dev/malcontent/blob/main/rules/shell/tmp_semicolon.yara#semicolon_short_tmp",
                    "ID": "shell/tmp_semicolon",
                    "RuleName": "semicolon_short_tmp"
                }
            ],
            "RiskScore": 3,
            "RiskLevel": "HIGH"
        },
        "/tmp/bubblewrap.zip4269052694/tests/test-seccomp.py": {
            "Path": "/tmp/bubblewrap.zip4269052694/tests/test-seccomp.py",
            "SHA256": "",
            "Size": 0,
            "RiskScore": 0
        },
        "/tmp/bubblewrap.zip4269052694/tests/test-specifying-pidns.sh": {
            "Path": "/tmp/bubblewrap.zip4269052694/tests/test-specifying-pidns.sh",
            "SHA256": "",
            "Size": 0,
            "RiskScore": 0
        },
        "/tmp/bubblewrap.zip4269052694/tests/test-specifying-userns.sh": {
            "Path": "/tmp/bubblewrap.zip4269052694/tests/test-specifying-userns.sh",
            "SHA256": "",
            "Size": 0,
            "RiskScore": 0
        },
        "/tmp/bubblewrap.zip4269052694/tests/test-utils.c": {
            "Path": "/tmp/bubblewrap.zip4269052694/tests/test-utils.c",
            "SHA256": "",
            "Size": 0,
            "RiskScore": 0
        },
        "/tmp/bubblewrap.zip4269052694/tests/try-syscall.c": {
            "Path": "/tmp/bubblewrap.zip4269052694/tests/try-syscall.c",
            "SHA256": "",
            "Size": 0,
            "RiskScore": 0
        },
        "/tmp/bubblewrap.zip4269052694/tests/use-as-subproject/.gitignore": {
            "Path": "/tmp/bubblewrap.zip4269052694/tests/use-as-subproject/.gitignore",
            "SHA256": "",
            "Size": 0,
            "Skipped": "data file",
            "RiskScore": 0
        },
        "/tmp/bubblewrap.zip4269052694/tests/use-as-subproject/README": {
            "Path": "/tmp/bubblewrap.zip4269052694/tests/use-as-subproject/README",
            "SHA256": "",
            "Size": 0,
            "Skipped": "data file",
            "RiskScore": 0
        },
        "/tmp/bubblewrap.zip4269052694/tests/use-as-subproject/assert-correct-rpath.py": {
            "Path": "/tmp/bubblewrap.zip4269052694/tests/use-as-subproject/assert-correct-rpath.py",
            "SHA256": "",
            "Size": 0,
            "RiskScore": 0
        },
        "/tmp/bubblewrap.zip4269052694/tests/use-as-subproject/config.h": {
            "Path": "/tmp/bubblewrap.zip4269052694/tests/use-as-subproject/config.h",
            "SHA256": "",
            "Size": 0,
            "RiskScore": 0
        },
        "/tmp/bubblewrap.zip4269052694/tests/use-as-subproject/dummy-config.h.in": {
            "Path": "/tmp/bubblewrap.zip4269052694/tests/use-as-subproject/dummy-config.h.in",
            "SHA256": "",
            "Size": 0,
            "Skipped": "data file",
            "RiskScore": 0
        },
        "/tmp/bubblewrap.zip4269052694/tests/use-as-subproject/meson.build": {
            "Path": "/tmp/bubblewrap.zip4269052694/tests/use-as-subproject/meson.build",
            "SHA256": "",
            "Size": 0,
            "Skipped": "data file",
            "RiskScore": 0
        },
        "/tmp/bubblewrap.zip4269052694/uncrustify.cfg": {
            "Path": "/tmp/bubblewrap.zip4269052694/uncrustify.cfg",
            "SHA256": "",
            "Size": 0,
            "Skipped": "data file",
            "RiskScore": 0
        },
        "/tmp/bubblewrap.zip4269052694/uncrustify.sh": {
            "Path": "/tmp/bubblewrap.zip4269052694/uncrustify.sh",
            "SHA256": "",
            "Size": 0,
            "RiskScore": 0
        },
        "/tmp/bubblewrap.zip4269052694/utils.c": {
            "Path": "/tmp/bubblewrap.zip4269052694/utils.c",
            "SHA256": "",
            "Size": 0,
            "RiskScore": 0
        },
        "/tmp/bubblewrap.zip4269052694/utils.h": {
            "Path": "/tmp/bubblewrap.zip4269052694/utils.h",
            "SHA256": "",
            "Size": 0,
            "RiskScore": 0
        }
    },
    "Filter": "false_positive,ignore"
}
